frame/__init__.py
frame/frame_selector.py
frame/version.py
frame_feature_selector-0.1.3.dist-info/LICENSE
frame_feature_selector-0.1.3.dist-info/METADATA
frame_feature_selector-0.1.3.dist-info/WHEEL
frame_feature_selector-0.1.3.dist-info/entry_points.txt
frame_feature_selector-0.1.3.dist-info/top_level.txt
frame_feature_selector-0.1.3.dist-info/RECORD
