Metadata-Version: 2.1
Name: frame-feature-selector
Version: 0.1.3
Summary: FRAME: A Hybrid Feature Selection Library Combining Forward Selection and RFE with XGBoost
Home-page: https://github.com/parulkumari2707/FRAME-FEATURE-SELECTOR
Author: Parul Kumari
Author-email: parulkumari2707@gmail.com
Project-URL: Bug Tracker, https://github.com/parulkumari2707/FRAME-FEATURE-SELECTOR/issues
Project-URL: Documentation, https://github.com/parulkumari2707/FRAME-FEATURE-SELECTOR#readme
Keywords: feature-selection machine-learning sklearn xgboost forward-selection rfe hybrid
Classifier: Programming Language :: Python :: 3
Classifier: License :: OSI Approved :: MIT License
Classifier: Operating System :: OS Independent
Classifier: Intended Audience :: Science/Research
Classifier: Intended Audience :: Developers
Classifier: Topic :: Scientific/Engineering :: Artificial Intelligence
Requires-Python: >=3.7
License-File: LICENSE
Requires-Dist: numpy
Requires-Dist: pandas
Requires-Dist: scikit-learn
Requires-Dist: xgboost
